flexidispatch/__init__.py
flexidispatch/_nbdev.py
flexidispatch/core.py
flexidispatch-0.0.5.dist-info/LICENSE
flexidispatch-0.0.5.dist-info/METADATA
flexidispatch-0.0.5.dist-info/WHEEL
flexidispatch-0.0.5.dist-info/entry_points.txt
flexidispatch-0.0.5.dist-info/top_level.txt
flexidispatch-0.0.5.dist-info/RECORD
